VIXRHeston/__init__.py
VIXRHeston/utils.py
vixrheston-0.1.2.dist-info/licenses/LICENSE
vixrheston-0.1.2.dist-info/METADATA
vixrheston-0.1.2.dist-info/WHEEL
vixrheston-0.1.2.dist-info/top_level.txt
vixrheston-0.1.2.dist-info/RECORD
