Metadata-Version: 2.4
Name: VIXRHeston
Version: 0.1.2
Summary: VIX term structure in the rough Heston model via Markovian approximation
License: MIT
Requires-Python: >=3.9
License-File: LICENSE
Requires-Dist: numpy
Requires-Dist: scipy
Dynamic: description
Dynamic: description-content-type
Dynamic: license
Dynamic: license-file
Dynamic: requires-dist
Dynamic: requires-python
Dynamic: summary
